ctidb/__init__.py
ctidb/custom.py
ctidb/decoder.py
ctidb/reader.py
ctidb-1.1.16.dist-info/LICENSE
ctidb-1.1.16.dist-info/METADATA
ctidb-1.1.16.dist-info/WHEEL
ctidb-1.1.16.dist-info/top_level.txt
ctidb-1.1.16.dist-info/RECORD
