Metadata-Version: 2.1
Name: ctidb
Version: 1.1.16
Summary: criminalip.ctidb reader
Home-page: https://github.com/aispera/ctidb
Author: aispera
Author-email: infra@aispera.com
License: Apache License, Version 2.0
Keywords: aispera,ctidb,criminalip
Platform: UNKNOWN
Classifier: License :: OSI Approved :: Apache Software License
Classifier: Programming Language :: Python :: 3
Classifier: Programming Language :: Python :: 3.6
Classifier: Programming Language :: Python :: 3.7
Classifier: Programming Language :: Python :: 3.8
Classifier: Programming Language :: Python :: 3.9
Classifier: Programming Language :: Python :: 3.10
Classifier: Programming Language :: Python :: 3.11
Requires-Python: >=3.6
License-File: LICENSE
